streamlit_gallery/__init__.py
streamlit_gallery/palette.py
streamlit_gallery/utils.py
streamlit_gallery-0.1.0.dist-info/WHEEL
streamlit_gallery-0.1.0.dist-info/METADATA
streamlit_gallery-0.1.0.dist-info/RECORD
